LICENSE
README.md
pyproject.toml
setup.cfg
setup.py
clichatgpt/__init__.py
clichatgpt/__main__.py
clichatgpt/chat.py
clichatgpt/cli.py
clichatgpt/errors.py
clichatgpt/parser.py
clichatgpt/printer.py
clichatgpt/session.py
clichatgpt/storage.py
clichatgpt/utils.py
clichatgpt.egg-info/PKG-INFO
clichatgpt.egg-info/SOURCES.txt
clichatgpt.egg-info/dependency_links.txt
clichatgpt.egg-info/entry_points.txt
clichatgpt.egg-info/requires.txt
clichatgpt.egg-info/top_level.txt