Metadata-Version: 2.1
Name: clichatgpt
Version: 0.1.1
Summary: CLI access to ChatGPT
Home-page: https://github.com/pchchv/clichatgpt
Project-URL: Documentation, https://github.com/pchchv/clichatgpt
Keywords: clichat chatgpt cli python
License-File: LICENSE
